ebbe/__init__.py
ebbe/benchmark.py
ebbe/decorators.py
ebbe/format.py
ebbe/func.py
ebbe/iter.py
ebbe/types.py
ebbe/utils.py
ebbe-1.15.0.dist-info/LICENSE.txt
ebbe-1.15.0.dist-info/METADATA
ebbe-1.15.0.dist-info/WHEEL
ebbe-1.15.0.dist-info/top_level.txt
ebbe-1.15.0.dist-info/zip-safe
ebbe-1.15.0.dist-info/RECORD
