Metadata-Version: 2.1
Name: ebbe
Version: 1.15.0
Summary: Collection of typical helper functions for python.
Home-page: http://github.com/Yomguithereal/ebbe
Author: Guillaume Plique
Author-email: kropotkinepiotr@gmail.com
License: MIT
Keywords: iter
Platform: UNKNOWN
Requires-Python: >=3.5
Requires-Dist: typing-extensions ; python_version<'3.10'
